truegaze/__init__.py
truegaze/cli.py
truegaze/utils.py
truegaze/data/adobe_mobile_sdk.schema
truegaze/plugins/__init__.py
truegaze/plugins/adobe_mobile_sdk.py
truegaze/plugins/base.py
truegaze/plugins/firebase.py
truegaze/plugins/weak_key.py
truegaze-0.1.7.dist-info/LICENSE
truegaze-0.1.7.dist-info/METADATA
truegaze-0.1.7.dist-info/WHEEL
truegaze-0.1.7.dist-info/entry_points.txt
truegaze-0.1.7.dist-info/top_level.txt
truegaze-0.1.7.dist-info/RECORD
