Metadata-Version: 2.1
Name: truegaze
Version: 0.1.7
Summary: Static analysis tool for Android/iOS apps focusing on security issues outside the source code.
Home-page: https://github.com/nightwatchcybersecurity/truegaze
Author: Nightwatch Cybersecurity
Author-email: research@nightwatchcybersecurity.com
License: Apache
Project-URL: Bug Reports, https://github.com/nightwatchcybersecurity/truegaze/issues
Project-URL: Source, https://github.com/nightwatchcybersecurity/truegaze
Platform: UNKNOWN
Classifier: Environment :: Console
Classifier: Development Status :: 3 - Alpha
Classifier: License :: OSI Approved :: Apache Software License
Classifier: Operating System :: OS Independent
Classifier: Programming Language :: Python :: 3.6
Classifier: Programming Language :: Python :: 3.7
Requires-Python: >=3.6
Requires-Dist: androguard (>=3.3.5)
Requires-Dist: asn1crypto (>=1.4.0)
Requires-Dist: beautifultable (>=1.0.0)
Requires-Dist: click (>=7.1.2)
Requires-Dist: cryptography (>=3.0)
Requires-Dist: jsonschema (>=3.2.0)
Requires-Dist: requests (>=2.24.0)
Requires-Dist: requests-mock (>=1.8.0)
Requires-Dist: pytest (>=5.4.3)
Requires-Dist: pytest-cov (>=2.10.0)
Requires-Dist: tldextract (>=2.2.2)
Requires-Dist: roca-detect (==1.2.12)
